dqtool/__init__.py
dqtool/Profilers/__init__.py
dqtool/Profilers/base_profiler.py
dqtool/Profilers/column_profiler.py
dqtool/Profilers/database_profiler.py
dqtool/Profilers/profilingconfig.py
dqtool/Profilers/table_profiler.py
dqtool/Query_builder/PSQL_queries.py
dqtool/Query_builder/__init__.py
dqtool/Query_builder/_init_.py
dqtool/Utils/__init__.py
dqtool/Utils/profile_store.py
dqtool/Utils/query_executor.py
dqtool/Utils/sql_helpers.py
dqtoolx-0.1.dist-info/METADATA
dqtoolx-0.1.dist-info/WHEEL
dqtoolx-0.1.dist-info/entry_points.txt
dqtoolx-0.1.dist-info/top_level.txt
dqtoolx-0.1.dist-info/RECORD
